0205NPU/rtl/00_TOP/TOP_hardware_defines.vh
`define NPU_IN_DW                   32
`define NPU_OUT_DW                  32
`define MAX_DAT_DW                  16
`define log2_MAX_DAT_DW             ($clog2(`MAX_DAT_DW))
`define MAX_WT_DW                   16
`define log2_MAX_WT_DW              ($clog2(`MAX_WT_DW))

`define log2_CH                     20
`define log2_H                      10
`define log2_W                      10
`define log2_P                      4
`define log2_S                      4
`define log2_K                      4
`define log2_ADDR                   (`log2_CH + `log2_H + `log2_W + 2)

///////////////////   POOL INTERNAL WIDTHS  ////////////////////
`define POOL_CALC_DW                32
`define POOL_CALC_MUL_DW            64

///////////////////   TB DEFAULT SETTINGS   ////////////////////
`define TB_POOL_CAL_HALF_CLK_PERIOD 10
`define TB_POOL_CAL_TIMEOUT_NS      1000000

///////////////////   ON-CHIP WT BUF  ////////////////////
`define SP_SRAM_NUM                 1
`define log2_TOTAL_SP_SRAM_BITS     (25) //= 32Mb
`define TOTAL_SP_SRAM_BITS          (1<<`log2_TOTAL_SP_SRAM_BITS)
`define SINGLE_SP_SRAM_BITS         (`TOTAL_SP_SRAM_BITS/`SP_SRAM_NUM)  
`define SINGLE_SP_SRAM_WIDTH        (128)
`define SINGLE_SP_SRAM_DEPTH        (`SINGLE_SP_SRAM_BITS/`SINGLE_SP_SRAM_WIDTH)

///////////////////   ON-CHIP DAT BUF  ////////////////////
`define DP_SRAM_NUM                 2
`define log2_TOTAL_DP_SRAM_BITS     (24) //= 16Mb
`define TOTAL_DP_SRAM_BITS          (1<<`log2_TOTAL_DP_SRAM_BITS)
`define SINGLE_DP_SRAM_BITS         (`TOTAL_DP_SRAM_BITS/`DP_SRAM_NUM)  
`define SINGLE_DP_SRAM_WIDTH        (128)
`define SINGLE_DP_SRAM_DEPTH        (`SINGLE_DP_SRAM_BITS/`SINGLE_DP_SRAM_WIDTH)

0205NPU/rtl/00_TOP/sirv_gnrl_dffs.v
 /*                                                                      
 Copyright 2018-2020 Nuclei System Technology, Inc.                
                                                                         
 Licensed under the Apache License, Version 2.0 (the "License");         
 you may not use this file except in compliance with the License.        
 You may obtain a copy of the License at                                 
                                                                         
     http://www.apache.org/licenses/LICENSE-2.0                          
                                                                         
  Unless required by applicable law or agreed to in writing, software    
 distributed under the License is distributed on an "AS IS" BASIS,       
 WITHOUT WARRANTIES OR CONDITIONS OF ANY KIND, either express or implied.
 See the License for the specific language governing permissions and     
 limitations under the License.                                          
 */                                                                      
                                                                         
                                                                         
                                                                         
//=====================================================================
//
// Designer   : Bob Hu
//
// Description:
//  All of the general DFF and Latch modules
//
// ====================================================================

//


//
// ===========================================================================
//
// Description:
//  Verilog module sirv_gnrl DFF with Load-enable and Reset
//  Default reset value is 1
//
// ===========================================================================

module sirv_gnrl_dfflrs # (
  parameter DW = 32
) (

  input               lden, 
  input      [DW-1:0] dnxt,
  output     [DW-1:0] qout,

  input               clk,
  input               rst_n
);

reg [DW-1:0] qout_r;

always @(posedge clk or negedge rst_n)
begin : DFFLRS_PROC
  if (rst_n == 1'b0)
    qout_r <= {DW{1'b1}};
  else if (lden == 1'b1)
    qout_r <= #1 dnxt;
end

assign qout = qout_r;
    

endmodule
// ===========================================================================
//
// Description:
//  Verilog module sirv_gnrl DFF with Load-enable and Reset
//  Default reset value is 0
//
// ===========================================================================

module sirv_gnrl_dfflr # (
  parameter DW = 32
) (

  input               lden, 
  input      [DW-1:0] dnxt,
  output     [DW-1:0] qout,

  input               clk,
  input               rst_n
);

reg [DW-1:0] qout_r;

always @(posedge clk or negedge rst_n)
begin : DFFLR_PROC
  if (rst_n == 1'b0)
    qout_r <= {DW{1'b0}};
  else if (lden == 1'b1)
    qout_r <= #1 dnxt;
end

assign qout = qout_r;
    

endmodule
// ===========================================================================
//
// Description:
//  Verilog module sirv_gnrl DFF with Load-enable, no reset 
//
// ===========================================================================

module sirv_gnrl_dffl # (
  parameter DW = 32
) (

  input               lden, 
  input      [DW-1:0] dnxt,
  output     [DW-1:0] qout,

  input               clk 
);

reg [DW-1:0] qout_r;

always @(posedge clk)
begin : DFFL_PROC
  if (lden == 1'b1)
    qout_r <= #1 dnxt;
end

assign qout = qout_r;
    

endmodule
// ===========================================================================
//
// Description:
//  Verilog module sirv_gnrl DFF with Reset, no load-enable
//  Default reset value is 1
//
// ===========================================================================

module sirv_gnrl_dffrs # (
  parameter DW = 32
) (

  input      [DW-1:0] dnxt,
  output     [DW-1:0] qout,

  input               clk,
  input               rst_n
);

reg [DW-1:0] qout_r;

always @(posedge clk or negedge rst_n)
begin : DFFRS_PROC
  if (rst_n == 1'b0)
    qout_r <= {DW{1'b1}};
  else                  
    qout_r <= #1 dnxt;
end

assign qout = qout_r;

endmodule
// ===========================================================================
//
// Description:
//  Verilog module sirv_gnrl DFF with Reset, no load-enable
//  Default reset value is 0
//
// ===========================================================================

module sirv_gnrl_dffr # (
  parameter DW = 32
) (

  input      [DW-1:0] dnxt,
  output     [DW-1:0] qout,

  input               clk,
  input               rst_n
);

reg [DW-1:0] qout_r;

always @(posedge clk or negedge rst_n)
begin : DFFR_PROC
  if (rst_n == 1'b0)
    qout_r <= {DW{1'b0}};
  else                  
    qout_r <= #1 dnxt;
end

assign qout = qout_r;

endmodule
// ===========================================================================
//
// Description:
//  Verilog module for general latch 
//
// ===========================================================================

module sirv_gnrl_ltch # (
  parameter DW = 32
) (

  //input               test_mode,
  input               lden, 
  input      [DW-1:0] dnxt,
  output     [DW-1:0] qout
);

reg [DW-1:0] qout_r;

always @ * 
begin : LTCH_PROC
  if (lden == 1'b1)
    qout_r <= dnxt;
end

//assign qout = test_mode ? dnxt : qout_r;
assign qout = qout_r;
    

endmodule

0205NPU/rtl/04_POOL/POOL_cal.v
`include "TOP_hardware_defines.vh"

module POOL_cal
(
    input                          clk       ,
    input                          rst_n     ,
					   
    input                          start     ,
    output                         working   ,
    output                         done      ,
					   
    input  [`log2_K    -1:0]       i_cfg_Kx   ,
    input  [`log2_K    -1:0]       i_cfg_Ky   ,
    input  [`log2_S    -1:0]       i_cfg_Sx   ,
    input  [`log2_S    -1:0]       i_cfg_Sy   ,
    input  [`log2_P    -1:0]       i_cfg_Px   ,
    input  [`log2_P    -1:0]       i_cfg_Py   ,
    input  [`log2_CH   -1:0]       i_cfg_CHin ,
    input  [`log2_H    -1:0]       i_cfg_Hin  ,
    input  [`log2_W    -1:0]       i_cfg_Win  ,
    input  [`log2_CH   -1:0]       i_cfg_CHout,
    input  [`log2_H    -1:0]       i_cfg_Hout ,
    input  [`log2_W    -1:0]       i_cfg_Wout ,
/////////////////////////////////////////////////////

    input                          i_dat_in_vld ,
    input  signed [`MAX_DAT_DW-1:0]i_dat_in_pkt , 
    input                          i_win_first  ,
    input                          i_win_last   ,

    output                         o_dat_out_vld,
    output signed [`MAX_DAT_DW-1:0]o_dat_out_pkt
);

localparam signed [`MAX_DAT_DW-1:0] MIN_SIGNED = {1'b1, {(`MAX_DAT_DW-1){1'b0}}};
wire signed [`MAX_DAT_DW-1:0] max_val;
wire dat_in_vld_safe = (i_dat_in_vld === 1'b1);
wire win_first_safe  = (i_win_first  === 1'b1);
wire win_last_safe   = (i_win_last   === 1'b1);

wire max_update = dat_in_vld_safe && ($signed(i_dat_in_pkt) > $signed(max_val));
wire max_en = win_first_safe || max_update;
wire signed [`MAX_DAT_DW-1:0] max_next =
    win_first_safe ? (dat_in_vld_safe ? i_dat_in_pkt : MIN_SIGNED) :
    (max_update ? i_dat_in_pkt : max_val);
wire signed [`MAX_DAT_DW-1:0] out_next = win_last_safe ? max_next : max_val;

assign working = 1'b0;
assign done    = 1'b0;

sirv_gnrl_dfflr #(.DW(`MAX_DAT_DW)) u_max_val (
    .lden (max_en),
    .dnxt (max_next),
    .qout (max_val),
    .clk  (clk),
    .rst_n(rst_n)
);

assign o_dat_out_vld = win_last_safe;
assign o_dat_out_pkt = out_next;

endmodule

0205NPU/tb/testbench_POOL_cal.sv
`timescale 1ns/1ps
`include "TOP_hardware_defines.vh"

module testbench_POOL_cal;

localparam signed [`MAX_DAT_DW-1:0] MIN_SIGNED = {1'b1, {(`MAX_DAT_DW-1){1'b0}}};

bit clk;
bit rst_n;

logic start;
wire  working;
wire  done;

logic [`log2_K-1:0]  i_cfg_Kx;
logic [`log2_K-1:0]  i_cfg_Ky;
logic [`log2_S-1:0]  i_cfg_Sx;
logic [`log2_S-1:0]  i_cfg_Sy;
logic [`log2_P-1:0]  i_cfg_Px;
logic [`log2_P-1:0]  i_cfg_Py;
logic [`log2_CH-1:0] i_cfg_CHin;
logic [`log2_H-1:0]  i_cfg_Hin;
logic [`log2_W-1:0]  i_cfg_Win;
logic [`log2_CH-1:0] i_cfg_CHout;
logic [`log2_H-1:0]  i_cfg_Hout;
logic [`log2_W-1:0]  i_cfg_Wout;

logic                           i_dat_in_vld;
logic signed [`MAX_DAT_DW-1:0]  i_dat_in_pkt;
logic                           i_win_first;
logic                           i_win_last;

wire                            o_dat_out_vld;
wire signed [`MAX_DAT_DW-1:0]   o_dat_out_pkt;

int total_cnt;
int pass_cnt;
int fail_cnt;

always #(`TB_POOL_CAL_HALF_CLK_PERIOD) clk = ~clk;

POOL_cal dut (
    .clk          (clk),
    .rst_n        (rst_n),
    .start        (start),
    .working      (working),
    .done         (done),
    .i_cfg_Kx     (i_cfg_Kx),
    .i_cfg_Ky     (i_cfg_Ky),
    .i_cfg_Sx     (i_cfg_Sx),
    .i_cfg_Sy     (i_cfg_Sy),
    .i_cfg_Px     (i_cfg_Px),
    .i_cfg_Py     (i_cfg_Py),
    .i_cfg_CHin   (i_cfg_CHin),
    .i_cfg_Hin    (i_cfg_Hin),
    .i_cfg_Win    (i_cfg_Win),
    .i_cfg_CHout  (i_cfg_CHout),
    .i_cfg_Hout   (i_cfg_Hout),
    .i_cfg_Wout   (i_cfg_Wout),
    .i_dat_in_vld (i_dat_in_vld),
    .i_dat_in_pkt (i_dat_in_pkt),
    .i_win_first  (i_win_first),
    .i_win_last   (i_win_last),
    .o_dat_out_vld(o_dat_out_vld),
    .o_dat_out_pkt(o_dat_out_pkt)
);

task automatic drive_beat(
    input logic                          vld,
    input logic signed [`MAX_DAT_DW-1:0] dat,
    input logic                          first,
    input logic                          last
);
begin
    i_dat_in_vld = vld;
    i_dat_in_pkt = dat;
    i_win_first  = first;
    i_win_last   = last;
    @(posedge clk);
end
endtask

task automatic check_last(
    input string tc_name,
    input logic signed [`MAX_DAT_DW-1:0] exp
);
begin
    total_cnt++;
    if ((o_dat_out_vld === 1'b1) && ($signed(o_dat_out_pkt) === $signed(exp))) begin
        pass_cnt++;
        $display("[PASS] %s exp=%0d got=%0d", tc_name, exp, o_dat_out_pkt);
    end else begin
        fail_cnt++;
        $display("[FAIL] %s exp=%0d got_vld=%b got=%0d", tc_name, exp, o_dat_out_vld, o_dat_out_pkt);
    end
end
endtask

`include "generated/pool_cal_cases_auto.vh"

initial begin
    clk = 0;
    rst_n = 0;

    start      = 1'b0;
    i_cfg_Kx   = '0;
    i_cfg_Ky   = '0;
    i_cfg_Sx   = '0;
    i_cfg_Sy   = '0;
    i_cfg_Px   = '0;
    i_cfg_Py   = '0;
    i_cfg_CHin = '0;
    i_cfg_Hin  = '0;
    i_cfg_Win  = '0;
    i_cfg_CHout= '0;
    i_cfg_Hout = '0;
    i_cfg_Wout = '0;

    i_dat_in_vld = 1'b0;
    i_dat_in_pkt = '0;
    i_win_first  = 1'b0;
    i_win_last   = 1'b0;

    total_cnt = 0;
    pass_cnt  = 0;
    fail_cnt  = 0;

    $dumpvars(0, testbench_POOL_cal);

    repeat(5) @(posedge clk);
    rst_n = 1'b1;

    // Config fields are not used by current POOL_cal implementation, but still drive legal values.
    i_cfg_Kx    = 3;
    i_cfg_Ky    = 3;
    i_cfg_Sx    = 1;
    i_cfg_Sy    = 1;
    i_cfg_Px    = 1;
    i_cfg_Py    = 1;
    i_cfg_CHin  = 1;
    i_cfg_Hin   = 8;
    i_cfg_Win   = 8;
    i_cfg_CHout = 1;
    i_cfg_Hout  = 8;
    i_cfg_Wout  = 8;

    run_auto_cases();

    $display("\n================ POOL_cal SUMMARY ================");
    $display("TOTAL=%0d PASS=%0d FAIL=%0d", total_cnt, pass_cnt, fail_cnt);
    $display("==================================================\n");

    if (fail_cnt == 0) begin
        $display("POOL_cal verification PASSED.");
    end else begin
        $error("POOL_cal verification FAILED.");
    end

    #20;
    $finish;
end

initial begin
    #(`TB_POOL_CAL_TIMEOUT_NS);
    $error("Timeout reached.");
    $finish;
end

endmodule

Pool.sim/sim_1/behav/xsim/dump.vcd
$date
   Fri Mar  6 10:46:26 2026
$end
$version
  2019.2
$end
$timescale
  1ps
$end
$scope module testbench_POOL_cal $end
$var reg 1 ! clk $end
$var reg 1 " rst_n $end
$var reg 1 # start $end
$var wire 1 $ working $end
$var wire 1 % done $end
$var reg 4 & i_cfg_Kx [3:0] $end
$var reg 4 ' i_cfg_Ky [3:0] $end
$var reg 4 ( i_cfg_Sx [3:0] $end
$var reg 4 ) i_cfg_Sy [3:0] $end
$var reg 4 * i_cfg_Px [3:0] $end
$var reg 4 + i_cfg_Py [3:0] $end
$var reg 20 , i_cfg_CHin [19:0] $end
$var reg 10 - i_cfg_Hin [9:0] $end
$var reg 10 . i_cfg_Win [9:0] $end
$var reg 20 / i_cfg_CHout [19:0] $end
$var reg 10 0 i_cfg_Hout [9:0] $end
$var reg 10 1 i_cfg_Wout [9:0] $end
$var reg 1 2 i_dat_in_vld $end
$var reg 16 3 i_dat_in_pkt [15:0] $end
$var reg 1 4 i_win_first $end
$var reg 1 5 i_win_last $end
$var wire 1 6 o_dat_out_vld $end
$var wire 16 7 o_dat_out_pkt [15:0] $end
$var reg 32 8 total_cnt $end
$var reg 32 9 pass_cnt $end
$var reg 32 : fail_cnt $end
$var parameter 16 ; MIN_SIGNED [15:0] $end
$scope module dut $end
$var wire 1 < clk $end
$var wire 1 = rst_n $end
$var wire 1 > start $end
$var wire 1 $ working $end
$var wire 1 % done $end
$var wire 4 ? i_cfg_Kx [3:0] $end
$var wire 4 @ i_cfg_Ky [3:0] $end
$var wire 4 A i_cfg_Sx [3:0] $end
$var wire 4 B i_cfg_Sy [3:0] $end
$var wire 4 C i_cfg_Px [3:0] $end
$var wire 4 D i_cfg_Py [3:0] $end
$var wire 20 E i_cfg_CHin [19:0] $end
$var wire 10 F i_cfg_Hin [9:0] $end
$var wire 10 G i_cfg_Win [9:0] $end
$var wire 20 H i_cfg_CHout [19:0] $end
$var wire 10 I i_cfg_Hout [9:0] $end
$var wire 10 J i_cfg_Wout [9:0] $end
$var wire 1 K i_dat_in_vld $end
$var wire 16 L i_dat_in_pkt [15:0] $end
$var wire 1 M i_win_first $end
$var wire 1 N i_win_last $end
$var wire 1 6 o_dat_out_vld $end
$var wire 16 7 o_dat_out_pkt [15:0] $end
$var wire 16 O max_val [15:0] $end
$var wire 1 P dat_in_vld_safe $end
$var wire 1 Q win_first_safe $end
$var wire 1 R win_last_safe $end
$var wire 1 S max_update $end
$var wire 1 T max_en $end
$var wire 16 U max_next [15:0] $end
$var wire 16 V out_next [15:0] $end
$var parameter 16 W MIN_SIGNED [15:0] $end
$scope module u_max_val $end
$var wire 1 T lden $end
$var wire 16 U dnxt [15:0] $end
$var wire 16 O qout [15:0] $end
$var wire 1 < clk $end
$var wire 1 = rst_n $end
$var reg 16 X qout_r [15:0] $end
$var parameter 32 Y DW [31:0] $end
$upscope $end
$upscope $end
$scope task drive_beat $end
$var reg 1 Z vld $end
$var reg 16 [ dat [15:0] $end
$var reg 1 \ first $end
$var reg 1 ] last $end
$upscope $end
$scope task check_last $end
$var reg 32 ^ tc_name $end
$var reg 16 [ exp [15:0] $end
$upscope $end
$scope task run_auto_cases $end
$upscope $end
$scope task xilinx_isim_temp_0_ln6_excessive_seqblock_chunk $end
$upscope $end
$scope task xilinx_isim_temp_1_ln6_excessive_seqblock_chunk $end
$upscope $end
$scope task xilinx_isim_temp_2_ln6_excessive_seqblock_chunk $end
$upscope $end
$scope task xilinx_isim_temp_3_ln6_excessive_seqblock_chunk $end
$upscope $end
$scope task xilinx_isim_temp_4_ln6_excessive_seqblock_chunk $end
$upscope $end
$scope task xilinx_isim_temp_5_ln6_excessive_seqblock_chunk $end
$upscope $end
$scope task xilinx_isim_temp_6_ln6_excessive_seqblock_chunk $end
$upscope $end
$scope task xilinx_isim_temp_7_ln6_excessive_seqblock_chunk $end
$upscope $end
$scope task xilinx_isim_temp_8_ln6_excessive_seqblock_chunk $end
$upscope $end
$scope task xilinx_isim_temp_9_ln6_excessive_seqblock_chunk $end
$upscope $end
$upscope $end
$enddefinitions $end
#0
$dumpvars
0!
0"
0#
0$
0%
b0 &
b0 '
b0 (
b0 )
b0 *
b0 +
b0 ,
b0 -
b0 .
b0 /
b0 0
b0 1
02
b0 3
04
05
06
b0 7
b0 8
b0 9
b0 :
b1000000000000000 ;
0<
0=
0>
b0 ?
b0 @
b0 A
b0 B
b0 C
b0 D
b0 E
b0 F
b0 G
b0 H
b0 I
b0 J
0K
b0 L
0M
0N
b0 O
0P
0Q
0R
0S
0T
b0 U
b0 V
b1000000000000000 W
b0 X
b10000 Y
0Z
b0 [
0\
0]
b0 ^
$end
#10000
1!
1<
#20000
0!
0<
#30000
1!
1<
#40000
0!
0<
#50000
1!
1<
#60000
0!
0<
#70000
1!
1<
#80000
0!
0<
#90000
1!
1"
b11 &
b11 '
b1 (
b1 )
b1 *
b1 +
b1 ,
b1000 -
b1000 .
b1 /
b1000 0
b1000 1
12
b101 3
14
15
16
b101 7
1<
1=
b11 ?
b11 @
b1 A
b1 B
b1 C
b1 D
b1 E
b1000 F
b1000 G
b1 H
b1000 I
b1000 J
1K
b101 L
1M
1N
1P
1Q
1R
1S
1T
b101 U
b101 V
#100000
0!
0<
#110000
1!
b11 3
05
06
b0 7
b1 8
b1 9
1<
b11 L
0N
0R
1S
b11 U
b0 V
#111000
b101 7
b101 O
0S
b11 U
b101 V
b101 X
#120000
0!
0<
#130000
1!
b1100 3
04
1<
b1100 L
0M
0Q
1S
b1100 U
b101 V
#131000
b11 7
b11 O
1S
b1100 U
b11 V
b11 X
#140000
0!
0<
#150000
1!
b111 3
15
16
b111 7
1<
b111 L
1N
1R
1S
b111 U
b111 V
#151000
b1100 7
b1100 O
0S
0T
b1100 U
b1100 V
b1100 X
#160000
0!
0<
#170000
1!
b1111111111111000 3
14
05
06
b10 8
b10 9
1<
b1111111111111000 L
1M
0N
1Q
0R
0S
1T
b1111111111111000 U
b1100 V
#180000
0!
0<
#190000
1!
b1111111111111101 3
04
1<
b1111111111111101 L
0M
0Q
0S
0T
b1100 U
b1100 V
#191000
b1111111111111000 7
b1111111111111000 O
1S
1T
b1111111111111101 U
b1111111111111000 V
b1111111111111000 X
#200000
0!
0<
#210000
1!
b1111111111101100 3
15
16
1<
b1111111111101100 L
1N
1R
0S
0T
b1111111111111000 U
b1111111111111000 V
#211000
b1111111111111101 7
b1111111111111101 O
0S
b1111111111111101 U
b1111111111111101 V
b1111111111111101 X
#220000
0!
0<
#230000
1!
02
b0 3
14
05
06
b11 8
b11 9
1<
0K
b0 L
1M
0N
0P
1Q
0R
0S
1T
b1000000000000000 U
b1111111111111101 V
#240000
0!
0<
#250000
1!
12
b1111111111111111 3
04
1<
1K
b1111111111111111 L
0M
1P
0Q
1S
1T
b1111111111111111 U
b1111111111111101 V
#251000
b1000000000000000 7
b1000000000000000 O
1S
b1111111111111111 U
b1000000000000000 V
b1000000000000000 X
#260000
0!
0<
#270000
1!
b100 3
15
16
b100 7
1<
b100 L
1N
1R
1S
b100 U
b100 V
#271000
b1111111111111111 O
1S
b100 U
b100 V
b1111111111111111 X
#280000
0!
0<
#290000
1!
02
b0 3
14
05
06
b1111111111111111 7
b100 8
b100 9
1<
0K
b0 L
1M
0N
0P
1Q
0R
0S
b1000000000000000 U
b1111111111111111 V
#291000
b100 7
b100 O
0S
b1000000000000000 U
b100 V
b100 X
#300000
0!
0<
#310000
1!
b0 3
04
1<
0M
0Q
0T
b100 U
b100 V
#311000
b1000000000000000 7
b1000000000000000 O
0S
b1000000000000000 U
b1000000000000000 V
b1000000000000000 X
#320000
0!
0<
#330000
1!
b0 3
15
16
1<
1N
1R
b1000000000000000 V
#340000
0!
0<
#350000
1!
12
b1001 3
14
05
06
b101 8
b101 9
1<
1K
b1001 L
1M
0N
1P
1Q
0R
1S
1T
b1001 U
b1000000000000000 V
#360000
0!
0<
#370000
1!
b1001 3
04
1<
0M
0Q
b1001 U
#371000
b1001 7
b1001 O
0S
0T
b1001 U
b1001 V
b1001 X
#380000
0!
0<
#390000
1!
b1000 3
15
16
1<
b1000 L
1N
1R
0S
b1001 U
b1001 V
#400000
0!
0<
#410000
1!
b1111111110011100 3
14
05
06
b110 8
b110 9
1<
b1111111110011100 L
1M
0N
1Q
0R
0S
1T
b1111111110011100 U
b1001 V
#420000
0!
0<
#430000
1!
b101101 3
04
1<
b101101 L
0M
0Q
1S
b101101 U
b1001 V
#431000
b1111111110011100 7
b1111111110011100 O
1S
b101101 U
b1111111110011100 V
b1111111110011100 X
#440000
0!
0<
#450000
1!
b10111 3
1<
b10111 L
1S
b10111 U
b1111111110011100 V
#451000
b101101 7
b101101 O
0S
0T
b101101 U
b101101 V
b101101 X
#460000
0!
0<
#470000
1!
b1100110 3
1<
b1100110 L
1S
1T
b1100110 U
b101101 V
#480000
0!
0<
#490000
1!
b1111111111111001 3
15
16
1<
b1111111111111001 L
1N
1R
0S
0T
b101101 U
b101101 V
#491000
b1100110 7
b1100110 O
0S
b1100110 U
b1100110 V
b1100110 X
#500000
0!
0<
#510000
1!
b10 3
14
05
06
b111 8
b111 9
1<
b10 L
1M
0N
1Q
0R
0S
1T
b10 U
b1100110 V
#520000
0!
0<
#530000
1!
x2
b111010100110000 3
04
1<
xK
b111010100110000 L
0M
0P
0Q
0S
0T
b1100110 U
b1100110 V
#531000
b10 7
b10 O
0S
b10 U
b10 V
b10 X
#540000
0!
0<
#550000
1!
12
b111 3
15
16
b111 7
1<
1K
b111 L
1N
1P
1R
1S
1T
b111 U
b111 V
#560000
0!
0<
#570000
1!
b1100010111001011 3
14
05
06
b10 7
b1000 8
b1000 9
1<
b1100010111001011 L
1M
0N
1Q
0R
0S
b1100010111001011 U
b10 V
#571000
b111 7
b111 O
0S
b1100010111001011 U
b111 V
b111 X
#580000
0!
0<
#590000
1!
b11111101101010 3
04
1<
b11111101101010 L
0M
0Q
1S
b11111101101010 U
b111 V
#591000
b1100010111001011 7
b1100010111001011 O
1S
b11111101101010 U
b1100010111001011 V
b1100010111001011 X
#600000
0!
0<
#610000
1!
b1111001001011110 3
1<
b1111001001011110 L
1S
b1111001001011110 U
b1100010111001011 V
#611000
b11111101101010 7
b11111101101010 O
0S
0T
b11111101101010 U
b11111101101010 V
b11111101101010 X
#620000
0!
0<
#630000
1!
b1101011111000100 3
1<
b1101011111000100 L
0S
b11111101101010 U
#640000
0!
0<
#650000
1!
02
b1011110011010011 3
1<
0K
b1011110011010011 L
0P
0S
b11111101101010 U
#660000
0!
0<
#670000
1!
b100101100011111 3
1<
b100101100011111 L
0S
b11111101101010 U
#680000
0!
0<
#690000
1!
12
b1111100000001 3
1<
1K
b1111100000001 L
1P
0S
b11111101101010 U
#700000
0!
0<
#710000
1!
b1110101000010010 3
1<
b1110101000010010 L
0S
b11111101101010 U
#720000
0!
0<
#730000
1!
02
b1110011111010001 3
1<
0K
b1110011111010001 L
0P
0S
b11111101101010 U
#740000
0!
0<
#750000
1!
12
b111000000001000 3
1<
1K
b111000000001000 L
1P
1S
1T
b111000000001000 U
b11111101101010 V
#760000
0!
0<
#770000
1!
b1110010000110101 3
15
16
1<
b1110010000110101 L
1N
1R
0S
0T
b11111101101010 U
b11111101101010 V
#771000
b111000000001000 7
b111000000001000 O
0S
b111000000001000 U
b111000000001000 V
b111000000001000 X
#780000
0!
0<
#790000
1!
b110100101111101 3
14
05
06
b1001 8
b1001 9
1<
b110100101111101 L
1M
0N
1Q
0R
0S
1T
b110100101111101 U
b111000000001000 V
#800000
0!
0<
#810000
1!
b1100100001010111 3
04
1<
b1100100001010111 L
0M
0Q
0S
0T
b111000000001000 U
b111000000001000 V
#811000
b110100101111101 7
b110100101111101 O
0S
b110100101111101 U
b110100101111101 V
b110100101111101 X
#820000
0!
0<
#830000
1!
b1000111111110001 3
1<
b1000111111110001 L
0S
b110100101111101 U
#840000
0!
0<
#850000
1!
02
b1001011110110110 3
1<
0K
b1001011110110110 L
0P
0S
b110100101111101 U
#860000
0!
0<
#870000
1!
b111010001110101 3
1<
b111010001110101 L
0S
b110100101111101 U
#880000
0!
0<
#890000
1!
b1100001100011010 3
1<
b1100001100011010 L
0S
b110100101111101 U
#900000
0!
0<
#910000
1!
12
b1000110100100101 3
1<
1K
b1000110100100101 L
1P
0S
b110100101111101 U
#920000
0!
0<
#930000
1!
b10001010101100 3
1<
b10001010101100 L
0S
b110100101111101 U
#940000
0!
0<
#950000
1!
02
b1000111100000110 3
1<
0K
b1000111100000110 L
0P
0S
b110100101111101 U
#960000
0!
0<
#970000
1!
12
b1010001011000100 3
1<
1K
b1010001011000100 L
1P
0S
b110100101111101 U
#980000
0!
0<
#990000
1!
b101100010010010 3
1<
b101100010010010 L
0S
b110100101111101 U
#1000000
0!
0<
#1010000
1!
02
b1010011111111011 3
15
16
1<
0K
b1010011111111011 L
1N
0P
1R
0S
b110100101111101 U
b110100101111101 V
#1020000
0!
0<
#1030000
1!
b1000000100011110 3
14
b1000000000000000 7
b1010 8
b1010 9
1<
b1000000100011110 L
1M
1Q
0S
1T
b1000000000000000 U
b1000000000000000 V
#1040000
0!
0<
#1050000
1!
12
b111010010011000 3
05
06
b110100101111101 7
b1011 8
b1011 9
1<
1K
b111010010011000 L
0N
1P
0R
1S
b111010010011000 U
b110100101111101 V
#1051000
b1000000000000000 7
b1000000000000000 O
1S
b111010010011000 U
b1000000000000000 V
b1000000000000000 X
#1060000
0!
0<
#1070000
1!
b10101110000001 3
04
15
16
b10101110000001 7
1<
b10101110000001 L
0M
1N
0Q
1R
1S
b10101110000001 U
b10101110000001 V
#1071000
b111010010011000 7
b111010010011000 O
0S
0T
b111010010011000 U
b111010010011000 V
b111010010011000 X
#1080000
0!
0<
#1090000
1!
b1010100001010010 3
14
05
06
b1100 8
b1100 9
1<
b1010100001010010 L
1M
0N
1Q
0R
0S
1T
b1010100001010010 U
b111010010011000 V
#1100000
0!
0<
#1110000
1!
02
b1001101111010011 3
04
15
16
1<
0K
b1001101111010011 L
0M
1N
0P
0Q
1R
0S
0T
b111010010011000 U
b111010010011000 V
#1111000
b1010100001010010 7
b1010100001010010 O
0S
b1010100001010010 U
b1010100001010010 V
b1010100001010010 X
#1120000
0!
0<
#1130000
1!
12
b1001011011110111 3
14
05
06
b1101 8
b1101 9
1<
1K
b1001011011110111 L
1M
0N
1P
1Q
0R
0S
1T
b1001011011110111 U
b1010100001010010 V
#1140000
0!
0<
#1150000
1!
b111100011101000 3
04
1<
b111100011101000 L
0M
0Q
1S
b111100011101000 U
b1010100001010010 V
#1151000
b1001011011110111 7
b1001011011110111 O
1S
b111100011101000 U
b1001011011110111 V
b1001011011110111 X
#1160000
0!
0<
#1170000
1!
02
b1100000000111001 3
1<
0K
b1100000000111001 L
0P
0S
0T
b1001011011110111 U
b1001011011110111 V
#1171000
b111100011101000 7
b111100011101000 O
0S
b111100011101000 U
b111100011101000 V
b111100011101000 X
#1180000
0!
0<
#1190000
1!
12
b110001111110001 3
1<
1K
b110001111110001 L
1P
0S
b111100011101000 U
#1200000
0!
0<
#1210000
1!
b10011011111001 3
1<
b10011011111001 L
0S
b111100011101000 U
#1220000
0!
0<
#1230000
1!
b1010001111100 3
1<
b1010001111100 L
0S
b111100011101000 U
#1240000
0!
0<
#1250000
1!
b1100010110110111 3
1<
b1100010110110111 L
0S
b111100011101000 U
#1260000
0!
0<
#1270000
1!
02
b1000011100111110 3
1<
0K
b1000011100111110 L
0P
0S
b111100011101000 U
#1280000
0!
0<
#1290000
1!
12
b1101001111000 3
1<
1K
b1101001111000 L
1P
0S
b111100011101000 U
#1300000
0!
0<
#1310000
1!
b1111010001110000 3
15
16
1<
b1111010001110000 L
1N
1R
0S
b111100011101000 U
b111100011101000 V
#1320000
0!
0<
#1330000
1!
b111101110000000 3
14
05
06
b1110 8
b1110 9
1<
b111101110000000 L
1M
0N
1Q
0R
1S
1T
b111101110000000 U
b111100011101000 V
#1340000
0!
0<
#1350000
1!
b1101000101001010 3
04
1<
b1101000101001010 L
0M
0Q
0S
0T
b111100011101000 U
b111100011101000 V
#1351000
b111101110000000 7
b111101110000000 O
0S
b111101110000000 U
b111101110000000 V
b111101110000000 X
#1360000
0!
0<
#1370000
1!
b1100100000011010 3
1<
b1100100000011010 L
0S
b111101110000000 U
#1380000
0!
0<
#1390000
1!
b1010000110110110 3
1<
b1010000110110110 L
0S
b111101110000000 U
#1400000
0!
0<
#1410000
1!
02
b101111011100110 3
1<
0K
b101111011100110 L
0P
0S
b111101110000000 U
#1420000
0!
0<
#1430000
1!
12
b100001011010100 3
1<
1K
b100001011010100 L
1P
0S
b111101110000000 U
#1440000
0!
0<
#1450000
1!
b100111011111001 3
1<
b100111011111001 L
0S
b111101110000000 U
#1460000
0!
0<
#1470000
1!
02
b1100001100101010 3
1<
0K
b1100001100101010 L
0P
0S
b111101110000000 U
#1480000
0!
0<
#1490000
1!
12
b1011110000001000 3
15
16
1<
1K
b1011110000001000 L
1N
1P
1R
0S
b111101110000000 U
b111101110000000 V
#1500000
0!
0<
